mhlabs_mcp_tools/__init__.py
mhlabs_mcp_tools/server.py
mhlabs_mcp_tools/core/__init__.py
mhlabs_mcp_tools/core/config.py
mhlabs_mcp_tools/core/constants.py
mhlabs_mcp_tools/core/prompts.py
mhlabs_mcp_tools/data/__init__.py
mhlabs_mcp_tools/data/external/__init__.py
mhlabs_mcp_tools/data/interim/__init__.py
mhlabs_mcp_tools/data/processed/__init__.py
mhlabs_mcp_tools/data/raw/__init__.py
mhlabs_mcp_tools/data/raw/contractions_dict.json
mhlabs_mcp_tools/data/raw/custom_substitutions.csv
mhlabs_mcp_tools/data/raw/leftovers_dict.json
mhlabs_mcp_tools/data/raw/slang_dict.json
mhlabs_mcp_tools/handlers/__init__.py
mhlabs_mcp_tools/handlers/custom_exceptions.py
mhlabs_mcp_tools/handlers/output_generator.py
mhlabs_mcp_tools/models/__init__.py
mhlabs_mcp_tools/nlp_components/__init__.py
mhlabs_mcp_tools/nlp_components/nlp_model.py
mhlabs_mcp_tools/services/__init__.py
mhlabs_mcp_tools/services/langchain_framework.py
mhlabs_mcp_tools/services/spacy_extractor.py
mhlabs_mcp_tools/text_preprocessing/__init__.py
mhlabs_mcp_tools/text_preprocessing/contractions.py
mhlabs_mcp_tools/text_preprocessing/emo_unicode.py
mhlabs_mcp_tools/text_preprocessing/slang_text.py
mhlabs_mcp_tools/text_preprocessing/text_preprocessing.py
mhlabs_mcp_tools-0.0.4.dist-info/licenses/LICENSE
mhlabs_mcp_tools-0.0.4.dist-info/METADATA
mhlabs_mcp_tools-0.0.4.dist-info/WHEEL
mhlabs_mcp_tools-0.0.4.dist-info/entry_points.txt
mhlabs_mcp_tools-0.0.4.dist-info/top_level.txt
mhlabs_mcp_tools-0.0.4.dist-info/RECORD
